{"metadata":{},"options":{"compact":false,"sourceMaps":true,"ast":true,"babelrc":false,"configFile":false,"parserOpts":{"sourceType":"module","sourceFileName":"C:\\Sandbox\\test\\imports\\ui\\pages\\messenger\\messenger.js","plugins":["*","flow","jsx","asyncGenerators","bigInt","classPrivateMethods","classPrivateProperties","classProperties","doExpressions","dynamicImport","exportDefaultFrom","exportExtensions","exportNamespaceFrom","functionBind","functionSent","importMeta","nullishCoalescingOperator","numericSeparator","objectRestSpread","optionalCatchBinding","optionalChaining",["pipelineOperator",{"proposal":"minimal"}],"throwExpressions","dynamicImport","classProperties","classPrivateProperties","jsx",["flow",{}],"asyncGenerators","objectRestSpread","objectRestSpread",["flow",{}],"asyncGenerators"],"allowImportExportEverywhere":true,"allowReturnOutsideFunction":true,"strictMode":false},"caller":{"name":"meteor","arch":"web.browser"},"sourceFileName":"imports/ui/pages/messenger/messenger.js","filename":"C:\\Sandbox\\test\\imports\\ui\\pages\\messenger\\messenger.js","passPerPreset":false,"envName":"development","cwd":"C:\\Sandbox\\test","root":"C:\\Sandbox\\test","plugins":[{"key":"base$0$0","visitor":{"Program":{"enter":[null]},"_exploded":true,"_verified":true},"options":{"generateLetDeclarations":true,"enforceStrictMode":false}},{"key":"transform-meteor-dynamic-import","visitor":{"_exploded":{},"_verified":{},"CallExpression":{"enter":[null]}},"options":{}},{"key":"transform-runtime","visitor":{"CallExpression":{"enter":[null]},"BinaryExpression":{"enter":[null]},"MemberExpression":{"enter":[null],"exit":[null]},"_exploded":true,"_verified":true,"Identifier":{"enter":[null]},"JSXIdentifier":{"enter":[null]}},"options":{}},{"key":"proposal-class-properties","visitor":{"PrivateName":{"enter":[null]},"_exploded":true,"_verified":true,"ClassDeclaration":{"enter":[null]},"ClassExpression":{"enter":[null]}},"options":{"loose":true}},{"key":"transform-modules-commonjs","visitor":{"Program":{"exit":[null]},"_exploded":true,"_verified":true},"options":{"allowTopLevelThis":true,"strictMode":false,"loose":true}},{"key":"transform-react-jsx","visitor":{"_exploded":{},"_verified":{},"JSXNamespacedName":{"enter":[null]},"JSXElement":{"exit":[null]},"JSXFragment":{"exit":[null]},"Program":{"enter":[null],"exit":[null]},"JSXAttribute":{"enter":[null]}},"options":{"pragma":"React.createElement","pragmaFrag":"React.Fragment","throwIfNamespace":true,"useBuiltIns":false}},{"key":"transform-react-display-name","visitor":{"ExportDefaultDeclaration":{"enter":[null]},"CallExpression":{"enter":[null]},"_exploded":true,"_verified":true},"options":{}},{"key":"syntax-flow","visitor":{"_exploded":true,"_verified":true},"options":{}},{"key":"syntax-async-generators","visitor":{"_exploded":true,"_verified":true},"options":{}},{"key":"syntax-object-rest-spread","visitor":{"_exploded":true,"_verified":true},"options":{}},{"key":"transform-for-of","visitor":{"ForOfStatement":{"enter":[null]},"_exploded":true,"_verified":true},"options":{"loose":true}},{"key":"transform-literals","visitor":{"NumericLiteral":{"enter":[null]},"StringLiteral":{"enter":[null]},"_exploded":true,"_verified":true},"options":{}},{"key":"transform-template-literals","visitor":{"TaggedTemplateExpression":{"enter":[null]},"TemplateLiteral":{"enter":[null]},"_exploded":true,"_verified":true},"options":{}},{"key":"transform-parameters","visitor":{"_exploded":true,"_verified":true,"FunctionDeclaration":{"enter":[null]},"FunctionExpression":{"enter":[null]},"ObjectMethod":{"enter":[null]},"ArrowFunctionExpression":{"enter":[null]},"ClassMethod":{"enter":[null]},"ClassPrivateMethod":{"enter":[null]}},"options":{}},{"key":"proposal-object-rest-spread","visitor":{"_exploded":{},"_verified":{},"VariableDeclarator":{"enter":[null]},"ExportNamedDeclaration":{"enter":[null]},"CatchClause":{"enter":[null]},"AssignmentExpression":{"enter":[null]},"ObjectExpression":{"enter":[null]},"FunctionDeclaration":{"enter":[null]},"FunctionExpression":{"enter":[null]},"ObjectMethod":{"enter":[null]},"ArrowFunctionExpression":{"enter":[null]},"ClassMethod":{"enter":[null]},"ClassPrivateMethod":{"enter":[null]},"ForInStatement":{"enter":[null]},"ForOfStatement":{"enter":[null]}},"options":{}},{"key":"transform-flow-strip-types","visitor":{"_exploded":{},"_verified":{},"Program":{"enter":[null]},"ImportDeclaration":{"enter":[null,null]},"ClassProperty":{"enter":[null]},"ClassPrivateProperty":{"enter":[null]},"AssignmentPattern":{"enter":[null]},"TypeCastExpression":{"enter":[null,null]},"CallExpression":{"enter":[null]},"OptionalCallExpression":{"enter":[null]},"NewExpression":{"enter":[null]},"ImportSpecifier":{"enter":[null]},"ClassDeclaration":{"enter":[null]},"ClassExpression":{"enter":[null]},"FunctionDeclaration":{"enter":[null]},"FunctionExpression":{"enter":[null]},"ObjectMethod":{"enter":[null]},"ArrowFunctionExpression":{"enter":[null]},"ClassMethod":{"enter":[null]},"ClassPrivateMethod":{"enter":[null]},"AnyTypeAnnotation":{"enter":[null]},"ArrayTypeAnnotation":{"enter":[null]},"BooleanTypeAnnotation":{"enter":[null]},"BooleanLiteralTypeAnnotation":{"enter":[null]},"NullLiteralTypeAnnotation":{"enter":[null]},"ClassImplements":{"enter":[null]},"DeclareClass":{"enter":[null]},"DeclareFunction":{"enter":[null]},"DeclareInterface":{"enter":[null]},"DeclareModule":{"enter":[null]},"DeclareModuleExports":{"enter":[null]},"DeclareTypeAlias":{"enter":[null]},"DeclareOpaqueType":{"enter":[null]},"DeclareVariable":{"enter":[null]},"DeclareExportDeclaration":{"enter":[null]},"DeclareExportAllDeclaration":{"enter":[null]},"DeclaredPredicate":{"enter":[null]},"ExistsTypeAnnotation":{"enter":[null]},"FunctionTypeAnnotation":{"enter":[null]},"FunctionTypeParam":{"enter":[null]},"GenericTypeAnnotation":{"enter":[null]},"InferredPredicate":{"enter":[null]},"InterfaceExtends":{"enter":[null]},"InterfaceDeclaration":{"enter":[null]},"InterfaceTypeAnnotation":{"enter":[null]},"IntersectionTypeAnnotation":{"enter":[null]},"MixedTypeAnnotation":{"enter":[null]},"EmptyTypeAnnotation":{"enter":[null]},"NullableTypeAnnotation":{"enter":[null]},"NumberLiteralTypeAnnotation":{"enter":[null]},"NumberTypeAnnotation":{"enter":[null]},"ObjectTypeAnnotation":{"enter":[null]},"ObjectTypeInternalSlot":{"enter":[null]},"ObjectTypeCallProperty":{"enter":[null]},"ObjectTypeIndexer":{"enter":[null]},"ObjectTypeProperty":{"enter":[null]},"ObjectTypeSpreadProperty":{"enter":[null]},"OpaqueType":{"enter":[null]},"QualifiedTypeIdentifier":{"enter":[null]},"StringLiteralTypeAnnotation":{"enter":[null]},"StringTypeAnnotation":{"enter":[null]},"ThisTypeAnnotation":{"enter":[null]},"TupleTypeAnnotation":{"enter":[null]},"TypeofTypeAnnotation":{"enter":[null]},"TypeAlias":{"enter":[null]},"TypeAnnotation":{"enter":[null]},"TypeParameter":{"enter":[null]},"TypeParameterDeclaration":{"enter":[null]},"TypeParameterInstantiation":{"enter":[null]},"UnionTypeAnnotation":{"enter":[null]},"Variance":{"enter":[null]},"VoidTypeAnnotation":{"enter":[null]},"ExportAllDeclaration":{"enter":[null]},"ExportDefaultDeclaration":{"enter":[null]},"ExportNamedDeclaration":{"enter":[null]}},"options":{}},{"key":"transform-exponentiation-operator","visitor":{"AssignmentExpression":{"enter":[null]},"BinaryExpression":{"enter":[null]},"_exploded":true,"_verified":true},"options":{}},{"key":"proposal-async-generator-functions","visitor":{"_exploded":{},"_verified":{},"Program":{"enter":[null]}},"options":{}}],"presets":[],"generatorOpts":{"filename":"C:\\Sandbox\\test\\imports\\ui\\pages\\messenger\\messenger.js","comments":true,"compact":false,"sourceMaps":true,"sourceFileName":"imports/ui/pages/messenger/messenger.js"}},"code":"module.link(\"./messenger.html\");\nlet User;\nmodule.link(\"/imports/api/user/user.js\", {\n  User(v) {\n    User = v;\n  }\n\n}, 0);\nlet Message;\nmodule.link(\"/imports/api/messages/messages.js\", {\n  Message(v) {\n    Message = v;\n  }\n\n}, 1);\nlet ReactiveVar;\nmodule.link(\"meteor/reactive-var\", {\n  ReactiveVar(v) {\n    ReactiveVar = v;\n  }\n\n}, 2);\nconst selectedUser = new ReactiveVar(undefined);\nconst searchUser = new ReactiveVar(\"\");\nTemplate.App_messenger.onCreated(function () {\n  var self = this;\n  self.autorun(function () {\n    Meteor.subscribe('users');\n    Meteor.subscribe('messages');\n  });\n});\nTemplate.App_messenger.helpers({\n  getUsers() {\n    var user_id = Session.get('u_l');\n    var groupChat = Session.all('u_l');\n    if (!user_id) return [];\n    var keywords = searchUser.get();\n    var query = {\n      _id: {\n        $ne: user_id\n      },\n      name: new RegExp('.*' + keywords + '.*', 'i')\n    };\n    return User.find(query);\n  },\n\n  getUserById(id) {\n    return User.findOne({\n      _id: id\n    });\n  },\n\n  getMessages() {\n    var user_id = Session.get('u_l');\n    var groupChat = user_id && groupChat;\n    if (!user_id) return [];\n    var query = {\n      $and: [{\n        $or: [{\n          sid: user_id\n        }, {\n          rid: user_id\n        }]\n      }]\n    };\n\n    var _selected_user = selectedUser.get();\n\n    if (!_selected_user) {\n      var fst = User.findOne({\n        _id: {\n          $ne: user_id\n        }\n      });\n      if (fst) _selected_user = fst._id;\n    }\n\n    if (_selected_user) query.$and.push({\n      $or: [{\n        sid: _selected_user\n      }, {\n        rid: _selected_user\n      }]\n    });\n    Meteor.setTimeout(function () {\n      jQuery(\".msg-wrap\").stop().animate({\n        scrollTop: jQuery(\".msg-wrap\")[0].scrollHeight\n      }, 500, 'swing');\n    }, 500);\n    return Message.find(query);\n  },\n\n  getLines(message) {\n    return message.split('\\n', '\\n');\n  },\n\n  isFile(type) {\n    return type == \"files\";\n  },\n\n  isImage(message) {\n    return /.+(png|jpg|jpeg|gif)/ig.test(message);\n  },\n\n  viewMessage(rid, message_id, viewed) {\n    var user_id = Session.get('u_l');\n\n    if (user_id === rid && !viewed) {\n      Meteor.call(\"message.update\", message_id, {\n        viewed: true\n      }, function () {\n        jQuery(\"#audio\")[0].play();\n        jQuery(\".msg-wrap\").stop().animate({\n          scrollTop: jQuery(\".msg-wrap\")[0].scrollHeight\n        }, 500, 'swing');\n      });\n    }\n  },\n\n  result() {\n    return Collection.find({\n      name: Session.get('name')\n    });\n  }\n\n});\nTemplate.App_messenger.events({\n  \"click #logout\"(evt) {\n    evt.preventDefault();\n    Session.clear('u_l');\n    return FlowRouter.go(\"/\");\n  },\n\n  \"click #send-message\"(evt, template) {\n    evt.preventDefault();\n    var selected_user_id = jQuery(\"#users\").val();\n    var select_user = jQuery(\"#users\").val();\n    var groupChat = jQuery(\"#users\").val();\n    var message = jQuery(\"#message\").val();\n    var sender_id = Session.get('u_l');\n    var upload = jQuery(\"#upload\")[0].files;\n    if (!sender_id || !selected_user_id || !select_user) return;\n    var update = jQuery(\"#send-message\").attr('update');\n\n    if (update && update != \"\") {\n      Meteor.call(\"message.update\", update, {\n        message: message\n      });\n    } else {\n      var type = \"text\";\n\n      if (upload.length) {\n        type = \"files\";\n        message = [];\n        Array.from(upload).forEach(function (file) {\n          uploadFile(file);\n          message.push(file.name);\n        });\n        message = message.join(\";\");\n      }\n\n      Meteor.call(\"message.insert\", sender_id, selected_user_id, groupChat, select_user, message, type);\n    }\n\n    jQuery(\"#message\").val('');\n    jQuery(\"#send-message\").text('Send');\n    jQuery(\"#send-message\").removeAttr('update');\n  },\n\n  \"click .remove\"() {\n    Meteor.call('message.remove', this._id);\n  },\n\n  \"change #users\"(evt) {\n    selectedUser.set(jQuery(\"#users\").val());\n  },\n\n  \"keyup #message\"(evt) {\n    if (!evt.shiftKey && (evt.keyCode === 13 || evt.which === 13) && !evt.ctrlKey === 17) {\n      jQuery(\"#send-message\").click();\n      evt.preventDefault();\n    }\n  },\n\n  \"click .update\"() {\n    jQuery(\"#message\").val(this.message);\n    jQuery(\"#send-message\").text('Update');\n    jQuery(\"#send-message\").attr('update', this._id);\n  },\n\n  \"click .submit\"() {\n    searchUser.set(jQuery(\".search\").val());\n  }\n\n});\n\nfunction uploadFile(file) {\n  var formData = new FormData();\n  formData.append(\"file\", file, file.name);\n  jQuery.ajax({\n    type: \"POST\",\n    url: \"http://127.0.0.1:3333/upload\",\n    success: function (data) {\n      jQuery(\"#upload[type=file]\").val(\"\");\n    },\n    error: function (error) {},\n    async: true,\n    data: formData,\n    cache: false,\n    contentType: false,\n    processData: false,\n    timeout: 60000\n  });\n}","map":{"version":3,"sources":["imports/ui/pages/messenger/messenger.js"],"names":["module","link","User","v","Message","ReactiveVar","selectedUser","undefined","searchUser","Template","App_messenger","onCreated","self","autorun","Meteor","subscribe","helpers","getUsers","user_id","Session","get","groupChat","all","keywords","query","_id","$ne","name","RegExp","find","getUserById","id","findOne","getMessages","$and","$or","sid","rid","_selected_user","fst","push","setTimeout","jQuery","stop","animate","scrollTop","scrollHeight","getLines","message","split","isFile","type","isImage","test","viewMessage","message_id","viewed","call","play","result","Collection","events","evt","preventDefault","clear","FlowRouter","go","template","selected_user_id","val","select_user","sender_id","upload","files","update","attr","length","Array","from","forEach","file","uploadFile","join","text","removeAttr","set","shiftKey","keyCode","which","ctrlKey","click","formData","FormData","append","ajax","url","success","data","error","async","cache","contentType","processData","timeout"],"mappings":"AAAAA,MAAM,CAACC,IAAP,CAAY,kBAAZ;AAAgC,IAAIC,IAAJ;AAASF,MAAM,CAACC,IAAP,CAAY,2BAAZ,EAAwC;AAACC,EAAAA,IAAI,CAACC,CAAD,EAAG;AAACD,IAAAA,IAAI,GAACC,CAAL;AAAO;;AAAhB,CAAxC,EAA0D,CAA1D;AAA6D,IAAIC,OAAJ;AAAYJ,MAAM,CAACC,IAAP,CAAY,mCAAZ,EAAgD;AAACG,EAAAA,OAAO,CAACD,CAAD,EAAG;AAACC,IAAAA,OAAO,GAACD,CAAR;AAAU;;AAAtB,CAAhD,EAAwE,CAAxE;AAA2E,IAAIE,WAAJ;AAAgBL,MAAM,CAACC,IAAP,CAAY,qBAAZ,EAAkC;AAACI,EAAAA,WAAW,CAACF,CAAD,EAAG;AAACE,IAAAA,WAAW,GAACF,CAAZ;AAAc;;AAA9B,CAAlC,EAAkE,CAAlE;AAK7M,MAAMG,YAAY,GAAG,IAAID,WAAJ,CAAgBE,SAAhB,CAArB;AACA,MAAMC,UAAU,GAAG,IAAIH,WAAJ,CAAgB,EAAhB,CAAnB;AAEAI,QAAQ,CAACC,aAAT,CAAuBC,SAAvB,CAAiC,YAAU;AACzC,MAAIC,IAAI,GAAG,IAAX;AACAA,EAAAA,IAAI,CAACC,OAAL,CAAa,YAAW;AACtBC,IAAAA,MAAM,CAACC,SAAP,CAAiB,OAAjB;AACAD,IAAAA,MAAM,CAACC,SAAP,CAAiB,UAAjB;AACD,GAHD;AAID,CAND;AAOAN,QAAQ,CAACC,aAAT,CAAuBM,OAAvB,CAA+B;AAC7BC,EAAAA,QAAQ,GAAE;AACR,QAAIC,OAAO,GAAGC,OAAO,CAACC,GAAR,CAAY,KAAZ,CAAd;AACA,QAAIC,SAAS,GAAGF,OAAO,CAACG,GAAR,CAAY,KAAZ,CAAhB;AACA,QAAG,CAACJ,OAAJ,EAAa,OAAO,EAAP;AACb,QAAIK,QAAQ,GAAGf,UAAU,CAACY,GAAX,EAAf;AACA,QAAII,KAAK,GAAG;AACVC,MAAAA,GAAG,EAAG;AAACC,QAAAA,GAAG,EAAER;AAAN,OADI;AAEVS,MAAAA,IAAI,EAAG,IAAIC,MAAJ,CAAW,OAAKL,QAAL,GAAc,IAAzB,EAA+B,GAA/B;AAFG,KAAZ;AAKA,WAAOrB,IAAI,CAAC2B,IAAL,CAAUL,KAAV,CAAP;AACD,GAZ4B;;AAa7BM,EAAAA,WAAW,CAACC,EAAD,EAAI;AACb,WAAO7B,IAAI,CAAC8B,OAAL,CAAa;AAACP,MAAAA,GAAG,EAAGM;AAAP,KAAb,CAAP;AACD,GAf4B;;AAgB7BE,EAAAA,WAAW,GAAE;AACX,QAAIf,OAAO,GAAGC,OAAO,CAACC,GAAR,CAAY,KAAZ,CAAd;AACA,QAAIC,SAAS,GAAGH,OAAO,IAAIG,SAA3B;AACA,QAAG,CAACH,OAAJ,EAAa,OAAO,EAAP;AACb,QAAIM,KAAK,GAAG;AACVU,MAAAA,IAAI,EAAG,CACL;AAACC,QAAAA,GAAG,EAAG,CAAC;AAACC,UAAAA,GAAG,EAAGlB;AAAP,SAAD,EAAkB;AAACmB,UAAAA,GAAG,EAAGnB;AAAP,SAAlB;AAAP,OADK;AADG,KAAZ;;AAKA,QAAIoB,cAAc,GAAGhC,YAAY,CAACc,GAAb,EAArB;;AACA,QAAG,CAACkB,cAAJ,EAAmB;AACjB,UAAIC,GAAG,GAAGrC,IAAI,CAAC8B,OAAL,CAAa;AAACP,QAAAA,GAAG,EAAG;AAACC,UAAAA,GAAG,EAAER;AAAN;AAAP,OAAb,CAAV;AACA,UAAGqB,GAAH,EAAQD,cAAc,GAAEC,GAAG,CAACd,GAApB;AACT;;AACD,QAAGa,cAAH,EAAmBd,KAAK,CAACU,IAAN,CAAWM,IAAX,CAAgB;AAACL,MAAAA,GAAG,EAAG,CAAC;AAACC,QAAAA,GAAG,EAAGE;AAAP,OAAD,EAAyB;AAACD,QAAAA,GAAG,EAAGC;AAAP,OAAzB;AAAP,KAAhB;AACnBxB,IAAAA,MAAM,CAAC2B,UAAP,CAAkB,YAAU;AAC1BC,MAAAA,MAAM,CAAC,WAAD,CAAN,CAAoBC,IAApB,GAA2BC,OAA3B,CAAmC;AAACC,QAAAA,SAAS,EAACH,MAAM,CAAC,WAAD,CAAN,CAAoB,CAApB,EAAuBI;AAAlC,OAAnC,EAAoF,GAApF,EAAyF,OAAzF;AACD,KAFD,EAEG,GAFH;AAGA,WAAO1C,OAAO,CAACyB,IAAR,CAAaL,KAAb,CAAP;AACD,GAnC4B;;AAoC7BuB,EAAAA,QAAQ,CAACC,OAAD,EAAS;AACf,WAAOA,OAAO,CAACC,KAAR,CAAc,IAAd,EAAmB,IAAnB,CAAP;AACD,GAtC4B;;AAuC7BC,EAAAA,MAAM,CAACC,IAAD,EAAM;AACV,WAAOA,IAAI,IAAI,OAAf;AACD,GAzC4B;;AA0C7BC,EAAAA,OAAO,CAACJ,OAAD,EAAS;AACd,WAAO,yBAAyBK,IAAzB,CAA8BL,OAA9B,CAAP;AACD,GA5C4B;;AA8C7BM,EAAAA,WAAW,CAACjB,GAAD,EAAMkB,UAAN,EAAkBC,MAAlB,EAAyB;AAClC,QAAItC,OAAO,GAAGC,OAAO,CAACC,GAAR,CAAY,KAAZ,CAAd;;AACA,QAAGF,OAAO,KAAKmB,GAAZ,IAAmB,CAACmB,MAAvB,EAA8B;AAC5B1C,MAAAA,MAAM,CAAC2C,IAAP,CAAY,gBAAZ,EAA8BF,UAA9B,EAA0C;AAACC,QAAAA,MAAM,EAAG;AAAV,OAA1C,EAA2D,YAAU;AACnEd,QAAAA,MAAM,CAAC,QAAD,CAAN,CAAiB,CAAjB,EAAoBgB,IAApB;AACAhB,QAAAA,MAAM,CAAC,WAAD,CAAN,CAAoBC,IAApB,GAA2BC,OAA3B,CAAmC;AAACC,UAAAA,SAAS,EAACH,MAAM,CAAC,WAAD,CAAN,CAAoB,CAApB,EAAuBI;AAAlC,SAAnC,EAAoF,GAApF,EAAyF,OAAzF;AACD,OAHD;AAID;AACF,GAtD4B;;AAuD7Ba,EAAAA,MAAM,GAAE;AACN,WAAOC,UAAU,CAAC/B,IAAX,CAAgB;AACrBF,MAAAA,IAAI,EAAGR,OAAO,CAACC,GAAR,CAAY,MAAZ;AADc,KAAhB,CAAP;AAGD;;AA3D4B,CAA/B;AA8DAX,QAAQ,CAACC,aAAT,CAAuBmD,MAAvB,CAA8B;AAC5B,kBAAgBC,GAAhB,EAAqB;AACnBA,IAAAA,GAAG,CAACC,cAAJ;AACA5C,IAAAA,OAAO,CAAC6C,KAAR,CAAc,KAAd;AACA,WAAOC,UAAU,CAACC,EAAX,CAAc,GAAd,CAAP;AACD,GAL2B;;AAM5B,wBAAsBJ,GAAtB,EAA2BK,QAA3B,EAAoC;AAClCL,IAAAA,GAAG,CAACC,cAAJ;AACA,QAAIK,gBAAgB,GAAG1B,MAAM,CAAC,QAAD,CAAN,CAAiB2B,GAAjB,EAAvB;AACA,QAAIC,WAAW,GAAG5B,MAAM,CAAC,QAAD,CAAN,CAAiB2B,GAAjB,EAAlB;AACA,QAAIhD,SAAS,GAAGqB,MAAM,CAAC,QAAD,CAAN,CAAiB2B,GAAjB,EAAhB;AACA,QAAIrB,OAAO,GAAGN,MAAM,CAAC,UAAD,CAAN,CAAmB2B,GAAnB,EAAd;AACA,QAAIE,SAAS,GAAGpD,OAAO,CAACC,GAAR,CAAY,KAAZ,CAAhB;AACA,QAAIoD,MAAM,GAAG9B,MAAM,CAAC,SAAD,CAAN,CAAkB,CAAlB,EAAqB+B,KAAlC;AACA,QAAG,CAACF,SAAD,IAAa,CAACH,gBAAd,IAAiC,CAACE,WAArC,EAAmD;AACnD,QAAII,MAAM,GAAGhC,MAAM,CAAC,eAAD,CAAN,CAAwBiC,IAAxB,CAA6B,QAA7B,CAAb;;AACA,QAAGD,MAAM,IAAIA,MAAM,IAAE,EAArB,EAAwB;AACtB5D,MAAAA,MAAM,CAAC2C,IAAP,CAAY,gBAAZ,EAA8BiB,MAA9B,EAAsC;AAAC1B,QAAAA,OAAO,EAACA;AAAT,OAAtC;AACD,KAFD,MAGI;AACF,UAAIG,IAAI,GAAG,MAAX;;AACA,UAAGqB,MAAM,CAACI,MAAV,EAAiB;AACfzB,QAAAA,IAAI,GAAG,OAAP;AACAH,QAAAA,OAAO,GAAG,EAAV;AACA6B,QAAAA,KAAK,CAACC,IAAN,CAAWN,MAAX,EAAmBO,OAAnB,CAA2B,UAASC,IAAT,EAAc;AACvCC,UAAAA,UAAU,CAACD,IAAD,CAAV;AACAhC,UAAAA,OAAO,CAACR,IAAR,CAAawC,IAAI,CAACrD,IAAlB;AACD,SAHD;AAIAqB,QAAAA,OAAO,GAAGA,OAAO,CAACkC,IAAR,CAAa,GAAb,CAAV;AACD;;AACDpE,MAAAA,MAAM,CAAC2C,IAAP,CAAY,gBAAZ,EAA8Bc,SAA9B,EAAyCH,gBAAzC,EAA0D/C,SAA1D,EAAqEiD,WAArE,EAAiFtB,OAAjF,EAA0FG,IAA1F;AACD;;AACDT,IAAAA,MAAM,CAAC,UAAD,CAAN,CAAmB2B,GAAnB,CAAuB,EAAvB;AACA3B,IAAAA,MAAM,CAAC,eAAD,CAAN,CAAwByC,IAAxB,CAA6B,MAA7B;AACAzC,IAAAA,MAAM,CAAC,eAAD,CAAN,CAAwB0C,UAAxB,CAAmC,QAAnC;AACD,GAnC2B;;AAoC5B,oBAAiB;AACftE,IAAAA,MAAM,CAAC2C,IAAP,CAAY,gBAAZ,EAA6B,KAAKhC,GAAlC;AACD,GAtC2B;;AAuC5B,kBAAgBqC,GAAhB,EAAoB;AAEhBxD,IAAAA,YAAY,CAAC+E,GAAb,CAAiB3C,MAAM,CAAC,QAAD,CAAN,CAAiB2B,GAAjB,EAAjB;AACH,GA1C2B;;AA2C5B,mBAAiBP,GAAjB,EAAqB;AACnB,QAAI,CAACA,GAAG,CAACwB,QAAL,KAAkBxB,GAAG,CAACyB,OAAJ,KAAgB,EAAhB,IAAsBzB,GAAG,CAAC0B,KAAJ,KAAc,EAAtD,KAA6D,CAAC1B,GAAG,CAAC2B,OAAL,KAAiB,EAAlF,EAAqF;AACnF/C,MAAAA,MAAM,CAAC,eAAD,CAAN,CAAwBgD,KAAxB;AACA5B,MAAAA,GAAG,CAACC,cAAJ;AACD;AACF,GAhD2B;;AAiD1B,oBAAiB;AACjBrB,IAAAA,MAAM,CAAC,UAAD,CAAN,CAAmB2B,GAAnB,CAAuB,KAAKrB,OAA5B;AACAN,IAAAA,MAAM,CAAC,eAAD,CAAN,CAAwByC,IAAxB,CAA6B,QAA7B;AACAzC,IAAAA,MAAM,CAAC,eAAD,CAAN,CAAwBiC,IAAxB,CAA6B,QAA7B,EAAuC,KAAKlD,GAA5C;AACD,GArD2B;;AAsD5B,oBAAiB;AACfjB,IAAAA,UAAU,CAAC6E,GAAX,CAAe3C,MAAM,CAAC,SAAD,CAAN,CAAkB2B,GAAlB,EAAf;AACD;;AAxD2B,CAA9B;;AA2DA,SAASY,UAAT,CAAoBD,IAApB,EAAyB;AACvB,MAAIW,QAAQ,GAAG,IAAIC,QAAJ,EAAf;AACAD,EAAAA,QAAQ,CAACE,MAAT,CAAgB,MAAhB,EAAwBb,IAAxB,EAA8BA,IAAI,CAACrD,IAAnC;AACAe,EAAAA,MAAM,CAACoD,IAAP,CAAY;AACV3C,IAAAA,IAAI,EAAE,MADI;AAEV4C,IAAAA,GAAG,EAAC,8BAFM;AAGVC,IAAAA,OAAO,EAAE,UAAUC,IAAV,EAAgB;AACzBvD,MAAAA,MAAM,CAAC,oBAAD,CAAN,CAA6B2B,GAA7B,CAAiC,EAAjC;AACC,KALS;AAMV6B,IAAAA,KAAK,EAAE,UAAUA,KAAV,EAAiB,CAAE,CANhB;AAOVC,IAAAA,KAAK,EAAE,IAPG;AAQVF,IAAAA,IAAI,EAAEN,QARI;AASVS,IAAAA,KAAK,EAAE,KATG;AAUVC,IAAAA,WAAW,EAAE,KAVH;AAWVC,IAAAA,WAAW,EAAE,KAXH;AAYVC,IAAAA,OAAO,EAAE;AAZC,GAAZ;AAcD","sourcesContent":["import './messenger.html';\r\nimport { User } from '/imports/api/user/user.js';\r\nimport { Message } from '/imports/api/messages/messages.js';\r\nimport { ReactiveVar } from 'meteor/reactive-var';\r\n\r\nconst selectedUser = new ReactiveVar(undefined);\r\nconst searchUser = new ReactiveVar(\"\");\r\n\r\nTemplate.App_messenger.onCreated(function(){\r\n  var self = this;\r\n  self.autorun(function() {\r\n    Meteor.subscribe('users');\r\n    Meteor.subscribe('messages');\r\n  });\r\n});\r\nTemplate.App_messenger.helpers({\r\n  getUsers(){\r\n    var user_id = Session.get('u_l');\r\n    var groupChat = Session.all('u_l');\r\n    if(!user_id) return [];\r\n    var keywords = searchUser.get();\r\n    var query = {\r\n      _id : {$ne: user_id},\r\n      name : new RegExp('.*'+keywords+'.*', 'i')\r\n    };\r\n\r\n    return User.find(query);\r\n  },\r\n  getUserById(id){\r\n    return User.findOne({_id : id});\r\n  },\r\n  getMessages(){\r\n    var user_id = Session.get('u_l');\r\n    var groupChat = user_id && groupChat;\r\n    if(!user_id) return [];\r\n    var query = {\r\n      $and : [\r\n        {$or : [{sid : user_id}, {rid : user_id}]}\r\n      ]\r\n    };\r\n    var _selected_user = selectedUser.get();\r\n    if(!_selected_user){\r\n      var fst = User.findOne({_id : {$ne: user_id}});\r\n      if(fst) _selected_user= fst._id;\r\n    }\r\n    if(_selected_user) query.$and.push({$or : [{sid : _selected_user}, {rid : _selected_user}]});\r\n    Meteor.setTimeout(function(){\r\n      jQuery(\".msg-wrap\").stop().animate({scrollTop:jQuery(\".msg-wrap\")[0].scrollHeight}, 500, 'swing');\r\n    }, 500)\r\n    return Message.find(query);\r\n  },\r\n  getLines(message){\r\n    return message.split('\\n','\\n');\r\n  },\r\n  isFile(type){\r\n    return type == \"files\";\r\n  },\r\n  isImage(message){\r\n    return /.+(png|jpg|jpeg|gif)/ig.test(message);\r\n  },\r\n\r\n  viewMessage(rid, message_id, viewed){\r\n    var user_id = Session.get('u_l');\r\n    if(user_id === rid && !viewed){\r\n      Meteor.call(\"message.update\", message_id, {viewed : true}, function(){\r\n        jQuery(\"#audio\")[0].play();\r\n        jQuery(\".msg-wrap\").stop().animate({scrollTop:jQuery(\".msg-wrap\")[0].scrollHeight}, 500, 'swing');\r\n      })\r\n    }\r\n  },\r\n  result(){\r\n    return Collection.find({\r\n      name : Session.get('name')\r\n    })\r\n  }\r\n});\r\n\r\nTemplate.App_messenger.events({\r\n  \"click #logout\"(evt) {\r\n    evt.preventDefault();\r\n    Session.clear('u_l')\r\n    return FlowRouter.go(\"/\");\r\n  },\r\n  \"click #send-message\"(evt, template){\r\n    evt.preventDefault();\r\n    var selected_user_id = jQuery(\"#users\").val();\r\n    var select_user = jQuery(\"#users\").val();\r\n    var groupChat = jQuery(\"#users\").val();\r\n    var message = jQuery(\"#message\").val();\r\n    var sender_id = Session.get('u_l');\r\n    var upload = jQuery(\"#upload\")[0].files;\r\n    if(!sender_id ||!selected_user_id ||!select_user ) return ;\r\n    var update = jQuery(\"#send-message\").attr('update');\r\n    if(update && update!=\"\"){\r\n      Meteor.call(\"message.update\", update, {message:message});\r\n    }\r\n    else{\r\n      var type = \"text\";\r\n      if(upload.length){\r\n        type = \"files\";\r\n        message = [];\r\n        Array.from(upload).forEach(function(file){\r\n          uploadFile(file);\r\n          message.push(file.name);\r\n        });\r\n        message = message.join(\";\");\r\n      }\r\n      Meteor.call(\"message.insert\", sender_id, selected_user_id,groupChat, select_user,message, type);\r\n    }\r\n    jQuery(\"#message\").val('');\r\n    jQuery(\"#send-message\").text('Send');\r\n    jQuery(\"#send-message\").removeAttr('update');\r\n  },\r\n  \"click .remove\"(){\r\n    Meteor.call('message.remove',this._id);\r\n  },\r\n  \"change #users\"(evt){\r\n\r\n      selectedUser.set(jQuery(\"#users\").val());\r\n  },\r\n  \"keyup #message\"(evt){\r\n    if (!evt.shiftKey && (evt.keyCode === 13 || evt.which === 13) && !evt.ctrlKey === 17){\r\n      jQuery(\"#send-message\").click();\r\n      evt.preventDefault();\r\n    }\r\n  },\r\n    \"click .update\"(){\r\n    jQuery(\"#message\").val(this.message);\r\n    jQuery(\"#send-message\").text('Update');\r\n    jQuery(\"#send-message\").attr('update', this._id);\r\n  },\r\n  \"click .submit\"(){\r\n    searchUser.set(jQuery(\".search\").val());\r\n  }\r\n});\r\n\r\nfunction uploadFile(file){\r\n  var formData = new FormData();\r\n  formData.append(\"file\", file, file.name);\r\n  jQuery.ajax({\r\n    type: \"POST\",\r\n    url:\"http://127.0.0.1:3333/upload\",\r\n    success: function (data) {\r\n    jQuery(\"#upload[type=file]\").val(\"\");\r\n    },\r\n    error: function (error) {},\r\n    async: true,\r\n    data: formData,\r\n    cache: false,\r\n    contentType: false,\r\n    processData: false,\r\n    timeout: 60000,\r\n  });\r\n}\r\n"]},"sourceType":"script","hash":"7ba27ce462eab869dfec3d2bcc3ef206a376ea20"}
